Metadata-Version: 1.1
Name: dabbiew
Version: 0.6.dev20171118
Summary: A curses-based DataFrame viewer inspired by TabView.
Home-page: https://github.com/agtumulak/dabbiew
Author: Aaron G. Tumulak
Author-email: agtumulak@gmail.com
License: MIT
Keywords: c,u,r,s,e,s, ,d,a,t,a,f,r,a,m,e, ,v,i,e,w,e,r
Platform: UNKNOWN
Classifier: Environment :: Console :: Curses
Classifier: License :: OSI Approved :: MIT License
Classifier: Programming Language :: Python :: 2.7
Classifier: Topic :: Database :: Front-Ends
